quicklook/__init__.py
quicklook/compat.py
quicklook/gls.py
quicklook/measure.py
quicklook/plot.py
quicklook/science.mplstyle
quicklook/tql.py
quicklook/utils.py
quicklook/data/TOIs.csv
quicklook/data/simbad_obj_types.csv
quicklook_package-1.4.dist-info/licenses/LICENSE
quicklook_package-1.4.dist-info/METADATA
quicklook_package-1.4.dist-info/WHEEL
quicklook_package-1.4.dist-info/top_level.txt
quicklook_package-1.4.dist-info/RECORD
