Metadata-Version: 2.4
Name: quicklook-package
Version: 1.4
Author-email: jpdeleon <jpdeleon.bsap@gmail.com>
Project-URL: Homepage, https://github.com/jpdeleon/quicklook
Classifier: Programming Language :: Python :: 3
Classifier: Operating System :: POSIX :: Linux
Classifier: Topic :: Scientific/Engineering :: Astronomy
Requires-Python: >=3.8
License-File: LICENSE
Requires-Dist: matplotlib
Requires-Dist: lightkurve==2.5
Requires-Dist: numpy==1.23
Requires-Dist: transitleastsquares==1.32
Requires-Dist: wotan==1.10
Requires-Dist: flammkuchen==1.0.3
Requires-Dist: reproject==0.12.0
Requires-Dist: astroplan==0.9
Requires-Dist: loguru
Requires-Dist: importlib_resources>=5.0.0
Provides-Extra: dev
Requires-Dist: pytest; extra == "dev"
Requires-Dist: pytest-benchmark; extra == "dev"
Requires-Dist: pytest-xdist; extra == "dev"
Requires-Dist: black; extra == "dev"
Requires-Dist: mypy; extra == "dev"
Requires-Dist: pre-commit; extra == "dev"
Requires-Dist: tox; extra == "dev"
Requires-Dist: ruff; extra == "dev"
Provides-Extra: notebooks
Requires-Dist: ipykernel; extra == "notebooks"
Requires-Dist: jupyter; extra == "notebooks"
Requires-Dist: nbconvert; extra == "notebooks"
Dynamic: license-file
